triton_utils/__init__.py
triton_utils/bench.py
triton_utils/dispatch.py
triton_utils/global_var.py
triton_utils/libentry.py
triton_utils/shape.py
triton_utils/test.py
triton_utils/test_mod.py
triton_utils-0.2.0.dist-info/LICENSE
triton_utils-0.2.0.dist-info/METADATA
triton_utils-0.2.0.dist-info/WHEEL
triton_utils-0.2.0.dist-info/top_level.txt
triton_utils-0.2.0.dist-info/RECORD
