Metadata-Version: 2.1
Name: triton_utils
Version: 0.2.0
Summary: A collection of utility functions and tools for Triton projects
Home-page: https://github.com/2niuhe/triton_utils
Author: 2niuhe
Author-email: carlton2tang@gmail.com
Project-URL: Bug Tracker, https://github.com/2niuhe/triton_utils/issues
Project-URL: repository, https://github.com/2niuhe/triton_utils
Classifier: Programming Language :: Python :: 3
Classifier: License :: OSI Approved :: MIT License
Classifier: Operating System :: POSIX :: Linux
Classifier: Intended Audience :: Developers
Classifier: Topic :: Software Development :: Libraries :: Python Modules
Requires-Python: >=3.7
License-File: LICENSE
Requires-Dist: numpy>=1.0.0
Requires-Dist: torch>=2.0.0
Requires-Dist: triton>=2.0.0
